cli.py
scorable_cli-0.1.6.dist-info/METADATA
scorable_cli-0.1.6.dist-info/WHEEL
scorable_cli-0.1.6.dist-info/entry_points.txt
scorable_cli-0.1.6.dist-info/top_level.txt
scorable_cli-0.1.6.dist-info/RECORD
