Metadata-Version: 2.4
Name: scorable-cli
Version: 0.1.6
Summary: CLI for the Scorable API
Author-email: Scorable <support@scorable.ai>
License: Apache-2.0
Project-URL: Homepage, https://scorable.ai/
Project-URL: Repository, https://github.com/root-signals/rs-sdk
Requires-Python: >=3.11
Requires-Dist: click
Requires-Dist: requests
Requires-Dist: pydantic
Requires-Dist: rich
Requires-Dist: pyyaml
Provides-Extra: dev
Requires-Dist: pytest>=8.4.1; extra == "dev"
Requires-Dist: pytest-mock>=3.14.1; extra == "dev"
